.gitattributes
.gitignore
.travis.yml
LICENSE
MANIFEST.in
README.md
setup.cfg
setup.py
ci/deploy_key.enc
docs/Makefile
docs/conf.py
docs/data.rst
docs/index.rst
docs/install.rst
docs/make.bat
docs/requirements.txt
docs/sample_usage.rst
docs/support.rst
docs/test.py
docs/tropycal_full_logo.png
docs/_static/dorian.png
docs/_static/grid_example_1.png
docs/_static/logo.png
docs/_static/logo_32.ico
docs/_static/michael_example_1.png
docs/_static/michael_example_2.png
docs/_static/michael_example_3.png
docs/_static/michael_example_4.png
docs/_static/storm_example_1.png
docs/_static/storm_example_2.png
docs/_static/storm_example_3.png
docs/_static/theme_override.css
docs/_static/tornado_example_1.png
docs/_static/tornado_example_2.png
docs/_static/tornado_example_3.png
docs/_static/tornado_example_5.png
docs/_static/trackdataset_example_1.png
docs/_static/trackdataset_example_2.png
docs/_static/trackdataset_example_3.png
docs/_static/trackdataset_example_4.png
docs/_static/css/badge_only.css
docs/_static/css/theme.css
docs/_static/css/fonts/Roboto-Slab-Bold.woff
docs/_static/css/fonts/Roboto-Slab-Bold.woff2
docs/_static/css/fonts/Roboto-Slab-Regular.woff
docs/_static/css/fonts/Roboto-Slab-Regular.woff2
docs/_static/css/fonts/fontawesome-webfont.eot
docs/_static/css/fonts/fontawesome-webfont.svg
docs/_static/css/fonts/fontawesome-webfont.ttf
docs/_static/css/fonts/fontawesome-webfont.woff
docs/_static/css/fonts/fontawesome-webfont.woff2
docs/_static/css/fonts/lato-bold-italic.woff
docs/_static/css/fonts/lato-bold-italic.woff2
docs/_static/css/fonts/lato-bold.woff
docs/_static/css/fonts/lato-bold.woff2
docs/_static/css/fonts/lato-normal-italic.woff
docs/_static/css/fonts/lato-normal-italic.woff2
docs/_static/css/fonts/lato-normal.woff
docs/_static/css/fonts/lato-normal.woff2
docs/_static/js/badge_only.js
docs/_static/js/theme.js
docs/_templates/autosummary/base.rst
docs/_templates/autosummary/class.rst
docs/_templates/autosummary/module.rst
src/tropycal.egg-info/PKG-INFO
src/tropycal.egg-info/SOURCES.txt
src/tropycal.egg-info/dependency_links.txt
src/tropycal.egg-info/requires.txt
src/tropycal.egg-info/top_level.txt
