Metadata-Version: 2.1
Name: tropycal
Version: 1.4
Summary: Package for retrieving and analyzing tropical cyclone data
Home-page: https://github.com/tropycal/tropycal
Author: Tomer Burg, Sam Lillo
Project-URL: Documentation, https://tropycal.github.io/tropycal/
Project-URL: Source Code, https://github.com/tropycal/tropycal
Keywords: meteorology,weather
Platform: any
Classifier: Programming Language :: Python
Classifier: Programming Language :: Python :: 3.6
Classifier: Programming Language :: Python :: 3.7
Classifier: Intended Audience :: Science/Research
Classifier: Operating System :: OS Independent
Requires-Python: >=3.6
License-File: LICENSE
